{"errors":[],"warnings":[],"namedChunkGroups":{"polyfill":{"chunks":[3,0,8],"assets":["webpack-runtime-5b9c9f5ad49828b8fa23.js","webpack-runtime-5b9c9f5ad49828b8fa23.js.map","commons-2522f49f39ba3b1206b3.js","commons-2522f49f39ba3b1206b3.js.map","polyfill-f98822240a27440a35b9.js","polyfill-f98822240a27440a35b9.js.map"],"children":{},"childAssets":{}},"app":{"chunks":[3,7,4],"assets":["webpack-runtime-5b9c9f5ad49828b8fa23.js","webpack-runtime-5b9c9f5ad49828b8fa23.js.map","framework-83e11af5cf111be5ad89.js","framework-83e11af5cf111be5ad89.js.map","app-e0154b97235cff07625e.js","app-e0154b97235cff07625e.js.map"],"children":{},"childAssets":{}},"component---src-pages-404-js":{"chunks":[2,1,0,5],"assets":["5e2a4920-af8585eda26774c525b4.js","5e2a4920-af8585eda26774c525b4.js.map","05d954cf-1780a4cc2dc4eca35f03.js","05d954cf-1780a4cc2dc4eca35f03.js.map","commons-2522f49f39ba3b1206b3.js","commons-2522f49f39ba3b1206b3.js.map","component---src-pages-404-js-85455bb2593648acae1b.js","component---src-pages-404-js-85455bb2593648acae1b.js.map"],"children":{},"childAssets":{}},"component---src-templates-article-js":{"chunks":[9,2,1,0,6],"assets":["styles.7f03f49f869028d8a33a.css","styles-bc72ca78f9bad9fb1f45.js","styles-bc72ca78f9bad9fb1f45.js.map","5e2a4920-af8585eda26774c525b4.js","5e2a4920-af8585eda26774c525b4.js.map","05d954cf-1780a4cc2dc4eca35f03.js","05d954cf-1780a4cc2dc4eca35f03.js.map","commons-2522f49f39ba3b1206b3.js","commons-2522f49f39ba3b1206b3.js.map","component---src-templates-article-js-7e2e8d7e5a0625025f4a.js","component---src-templates-article-js-7e2e8d7e5a0625025f4a.js.map"],"children":{},"childAssets":{}}},"assetsByChunkName":{"polyfill":["webpack-runtime-5b9c9f5ad49828b8fa23.js","commons-2522f49f39ba3b1206b3.js","polyfill-f98822240a27440a35b9.js"],"app":["webpack-runtime-5b9c9f5ad49828b8fa23.js","framework-83e11af5cf111be5ad89.js","app-e0154b97235cff07625e.js"],"component---src-pages-404-js":["5e2a4920-af8585eda26774c525b4.js","05d954cf-1780a4cc2dc4eca35f03.js","commons-2522f49f39ba3b1206b3.js","component---src-pages-404-js-85455bb2593648acae1b.js"],"component---src-templates-article-js":["styles.7f03f49f869028d8a33a.css","styles-bc72ca78f9bad9fb1f45.js","5e2a4920-af8585eda26774c525b4.js","05d954cf-1780a4cc2dc4eca35f03.js","commons-2522f49f39ba3b1206b3.js","component---src-templates-article-js-7e2e8d7e5a0625025f4a.js"]}}